src/TinyPNG.py
src/__init__.py
src/app.py
OrzTinyPNG-0.0.5.dist-info/LICENSE
OrzTinyPNG-0.0.5.dist-info/METADATA
OrzTinyPNG-0.0.5.dist-info/WHEEL
OrzTinyPNG-0.0.5.dist-info/entry_points.txt
OrzTinyPNG-0.0.5.dist-info/top_level.txt
OrzTinyPNG-0.0.5.dist-info/RECORD
