Metadata-Version: 2.1
Name: OrzTinyPNG
Version: 0.0.5
Summary: A tool for compress image such as png and jpg using TinyPNG API
Home-page: https://github.com/OrzGeeker/OrzTinyPNG
Author: wangzhizhou
Author-email: 824219521@qq.com
License: UNKNOWN
Platform: UNKNOWN
Classifier: Programming Language :: Python :: 3
Classifier: License :: OSI Approved :: MIT License
Classifier: Operating System :: OS Independent
Requires-Python: >=3, <4
Requires-Dist: twine
Requires-Dist: tinify
